promptpack_for_code/__init__.py
promptpack_for_code/__main__.py
promptpack_for_code/core.py
promptpack_for_code-2.1.1.dist-info/licenses/LICENSE
promptpack_for_code-2.1.1.dist-info/METADATA
promptpack_for_code-2.1.1.dist-info/WHEEL
promptpack_for_code-2.1.1.dist-info/entry_points.txt
promptpack_for_code-2.1.1.dist-info/top_level.txt
promptpack_for_code-2.1.1.dist-info/RECORD
