Metadata-Version: 2.4
Name: promptpack-for-code
Version: 2.1.1
Summary: A tool to bundle code files into a single file for AI analysis
Home-page: https://github.com/changyy/py-promptpack-for-code
Author: Yuan-Yi Chang
Author-email: changyy.csie@gmail.com
Project-URL: Bug Tracker, https://github.com/changyy/py-promptpack-for-code/issues
Project-URL: Documentation, https://github.com/changyy/py-promptpack-for-code#readme
Project-URL: Source Code, https://github.com/changyy/py-promptpack-for-code
Keywords: ai,code-review,static-analysis,development-tools
Classifier: Development Status :: 4 - Beta
Classifier: Intended Audience :: Developers
Classifier: Intended Audience :: Information Technology
Classifier: License :: OSI Approved :: MIT License
Classifier: Programming Language :: Python :: 3
Classifier: Programming Language :: Python :: 3.6
Classifier: Programming Language :: Python :: 3.7
Classifier: Programming Language :: Python :: 3.8
Classifier: Programming Language :: Python :: 3.9
Classifier: Programming Language :: Python :: 3.10
Classifier: Programming Language :: Python :: 3.11
Classifier: Programming Language :: Python :: 3.12
Classifier: Operating System :: OS Independent
Classifier: Topic :: Software Development :: Libraries :: Python Modules
Classifier: Topic :: Software Development :: Code Generators
Classifier: Topic :: Utilities
Requires-Python: >=3.6
License-File: LICENSE
Requires-Dist: tqdm
Dynamic: author
Dynamic: author-email
Dynamic: classifier
Dynamic: description
Dynamic: description-content-type
Dynamic: home-page
Dynamic: keywords
Dynamic: license-file
Dynamic: project-url
Dynamic: requires-dist
Dynamic: requires-python
Dynamic: summary
